teslajsonpy/__init__.py
teslajsonpy/__version__.py
teslajsonpy/car.py
teslajsonpy/connection.py
teslajsonpy/const.py
teslajsonpy/controller.py
teslajsonpy/endpoints.json
teslajsonpy/energy.py
teslajsonpy/exceptions.py
teslajsonpy/teslaproxy.py
teslajsonpy/test.json
teslajsonpy-3.13.2.dist-info/AUTHORS.md
teslajsonpy-3.13.2.dist-info/LICENSE
teslajsonpy-3.13.2.dist-info/METADATA
teslajsonpy-3.13.2.dist-info/WHEEL
teslajsonpy-3.13.2.dist-info/RECORD
