Metadata-Version: 2.3
Name: teslajsonpy
Version: 3.13.2
Summary: A library to work with Tesla API.
License: Apache-2.0
Author: Sergey Isachenko
Author-email: sergey.isachenkol@bool.by
Requires-Python: >=3.7,<4.0
Classifier: Development Status :: 3 - Alpha
Classifier: Environment :: Console
Classifier: Intended Audience :: Developers
Classifier: License :: OSI Approved :: Apache Software License
Classifier: Natural Language :: English
Classifier: Operating System :: OS Independent
Classifier: Programming Language :: Python :: 3
Classifier: Programming Language :: Python :: 3.7
Classifier: Programming Language :: Python :: 3.8
Classifier: Programming Language :: Python :: 3.9
Classifier: Programming Language :: Python :: 3.10
Classifier: Programming Language :: Python :: 3.11
Classifier: Programming Language :: Python :: 3.12
Classifier: Programming Language :: Python :: 3.13
Classifier: Programming Language :: Python :: 3 :: Only
Classifier: Topic :: Software Development :: Libraries :: Python Modules
Requires-Dist: aiohttp (>=3.7.4)
Requires-Dist: authcaptureproxy (>=1.1.3)
Requires-Dist: beautifulsoup4 (>=4.9.3)
Requires-Dist: httpx (>=0.17.1,<1.0)
Requires-Dist: orjson (>=3.8.5)
Requires-Dist: tenacity (>=8.1.0)
Requires-Dist: wrapt (>=1.12.1)
Project-URL: Documentation, https://teslajsonpy.readthedocs.io
Project-URL: Homepage, https://github.com/zabuldon/teslajsonpy
Project-URL: Repository, https://github.com/zabuldon/teslajsonpy
